build_django/__init__.py
build_django/__main__.py
build_django/const.py
build_django/utils/__init__.py
build_django/utils/files.py
build_django/utils/git.py
build_django/utils/process.py
build_django/utils/shell.py
build_django/utils/system.py
build_django-3.3.0.dist-info/LICENSE
build_django-3.3.0.dist-info/METADATA
build_django-3.3.0.dist-info/WHEEL
build_django-3.3.0.dist-info/entry_points.txt
build_django-3.3.0.dist-info/top_level.txt
build_django-3.3.0.dist-info/RECORD
