Metadata-Version: 2.1
Name: build-django
Version: 3.3.0
Summary: Command line utility for building Django projects
Home-page: https://notabug.org/kapustlo/build-django
Author: Kapustlo
Keywords: python,django,build,cli,generate,code
Classifier: Framework :: Django
Classifier: License :: OSI Approved :: GNU General Public License v3 (GPLv3)
Classifier: Topic :: Software Development :: Code Generators
Classifier: Environment :: Console
Classifier: Development Status :: 5 - Production/Stable
Classifier: Intended Audience :: Developers
Classifier: Programming Language :: Python :: 3.9
Classifier: Operating System :: POSIX :: Linux
Classifier: Natural Language :: English
Requires-Python: >=3.9
License-File: LICENSE
Requires-Dist: django
Requires-Dist: aiofiles
